EaseExcel/src/Excel/__inti__.py
EaseExcel/src/Excel/ease_excel.py
EaseExcel-1.0.2.dist-info/LICENSE
EaseExcel-1.0.2.dist-info/METADATA
EaseExcel-1.0.2.dist-info/WHEEL
EaseExcel-1.0.2.dist-info/top_level.txt
EaseExcel-1.0.2.dist-info/RECORD
