Metadata-Version: 2.1
Name: EaseExcel
Version: 1.0.2
Summary: Package to write data from database to excel files
Home-page: https://github.com/Vishal-Vashisht/EaseExcel
Author: Vishal Sharma
Author-email: vashisth671@gmail.com
License: MIT
Classifier: Development Status :: 5 - Production/Stable
Classifier: Intended Audience :: Developers
Classifier: Programming Language :: Python :: 3
Classifier: Operating System :: Unix
Classifier: Operating System :: MacOS :: MacOS X
Classifier: Operating System :: Microsoft :: Windows
Requires-Python: >=3.6
License-File: LICENSE
Requires-Dist: sqlalchemy
Requires-Dist: XlsxWriter
